rplus_utils/__init__.py
rplus_utils/custom_exception/__init__.py
rplus_utils/custom_exception/custom_exception.py
rplus_utils/jwt/__init__.py
rplus_utils/jwt/jwt.py
rplus_utils/logger/__init__.py
rplus_utils/logger/logger.py
rplus_utils/services/__init__.py
rplus_utils/services/http_services.py
rplus_utils/services/s3_db_services.py
rplus_utils/services/s3_services.py
rplus_utils/utils/__init__.py
rplus_utils/utils/util.py
rplus_utils_module-0.0.3.dist-info/WHEEL
rplus_utils_module-0.0.3.dist-info/METADATA
rplus_utils_module-0.0.3.dist-info/RECORD
